{
  "path": "gokuTranspo2.png",
  "spriteNumber": 2,
  "spriteSizeX": 247,
  "spriteSizeY": 0,
  "sprites": [
    {
      "SpritePosX": 0,
      "SpritePosY": 0,
      "SpriteSizeX": 247,
      "SpriteSizeY": 247,
      "BodyPosX": 31.891883850097656,
      "BodyPosY": 165.1350860595703,
      "BodySizeX": 21.62161636352539,
      "BodySizeY": 17.027023315429688,
      "rectangles": []
    },
    {
      "SpritePosX": 247,
      "SpritePosY": 0,
      "SpriteSizeX": 247,
      "SpriteSizeY": 247,
      "BodyPosX": 1.1080474853515625,
      "BodyPosY": 129.99996948242188,
      "BodySizeX": 82.16212463378906,
      "BodySizeY": 116.4864501953125,
      "rectangles": [
        {
          "type": "defenseBody",
          "posX": 20.026947021484375,
          "posY": 193.51345825195312,
          "sizeX": 17.83783,
          "sizeY": 52.162155
        },
        {
          "type": "defenseBody",
          "posX": 31.461456298828125,
          "posY": 142.6922607421875,
          "sizeX": 38.461517,
          "sizeY": 51.34613
        },
        {
          "type": "defenseBody",
          "posX": 40.11529541015625,
          "posY": 194.61532592773438,
          "sizeX": 12.884613,
          "sizeY": 22.884598
        },
        {
          "type": "defenseBody",
          "posX": 2.61529541015625,
          "posY": 164.99993896484375,
          "sizeX": 28.076935,
          "sizeY": 15.384613
        }
      ]
    }
  ]
}